{"records":[{"fields":{"Audio":[{"url": "https://label-pomona.s3-ap-southeast-2.amazonaws.com/Crossroad-070419_221502-S85-E98.wav"}],"Call Type":"Male","File Name":"Crossroad-070419_221502-S85-E98","Image":[{"url":"https://label-pomona.s3-ap-southeast-2.amazonaws.com/Crossroad-070419_221502-S85-E98.png"}],"Length (seconds)":13,"Start Time": "2019-04-07T22:16:27","Trap Number": "Secretary_Island/Crossroad" }},{"fields":{"Audio":[{"url": "https://label-pomona.s3-ap-southeast-2.amazonaws.com/Crossroad-070419_221502-S100-E107.wav"}],"Call Type":"Male","File Name":"Crossroad-070419_221502-S100-E107","Image":[{"url":"https://label-pomona.s3-ap-southeast-2.amazonaws.com/Crossroad-070419_221502-S100-E107.png"}],"Length (seconds)":7,"Start Time": "2019-04-07T22:16:42","Trap Number": "Secretary_Island/Crossroad" }},{"fields":{"Audio":[{"url": "https://label-pomona.s3-ap-southeast-2.amazonaws.com/Crossroad-070419_221502-S149-E156.wav"}],"Call Type":"Male","File Name":"Crossroad-070419_221502-S149-E156","Image":[{"url":"https://label-pomona.s3-ap-southeast-2.amazonaws.com/Crossroad-070419_221502-S149-E156.png"}],"Length (seconds)":7,"Start Time": "2019-04-07T22:17:31","Trap Number": "Secretary_Island/Crossroad" }},{"fields":{"Audio":[{"url": "https://label-pomona.s3-ap-southeast-2.amazonaws.com/Crossroad-070419_221502-S231-E238.wav"}],"Call Type":"Male","File Name":"Crossroad-070419_221502-S231-E238","Image":[{"url":"https://label-pomona.s3-ap-southeast-2.amazonaws.com/Crossroad-070419_221502-S231-E238.png"}],"Length (seconds)":7,"Start Time": "2019-04-07T22:18:53","Trap Number": "Secretary_Island/Crossroad" }},{"fields":{"Audio":[{"url": "https://label-pomona.s3-ap-southeast-2.amazonaws.com/Crossroad-070419_221502-S346-E353.wav"}],"Call Type":"Male","File Name":"Crossroad-070419_221502-S346-E353","Image":[{"url":"https://label-pomona.s3-ap-southeast-2.amazonaws.com/Crossroad-070419_221502-S346-E353.png"}],"Length (seconds)":7,"Start Time": "2019-04-07T22:20:48","Trap Number": "Secretary_Island/Crossroad" }},{"fields":{"Audio":[{"url": "https://label-pomona.s3-ap-southeast-2.amazonaws.com/Crossroad-070419_221502-S357-E375.wav"}],"Call Type":"Male","File Name":"Crossroad-070419_221502-S357-E375","Image":[{"url":"https://label-pomona.s3-ap-southeast-2.amazonaws.com/Crossroad-070419_221502-S357-E375.png"}],"Length (seconds)":18,"Start Time": "2019-04-07T22:20:59","Trap Number": "Secretary_Island/Crossroad" }},{"fields":{"Audio":[{"url": "https://label-pomona.s3-ap-southeast-2.amazonaws.com/Crossroad-070419_221502-S437-E444.wav"}],"Call Type":"Male","File Name":"Crossroad-070419_221502-S437-E444","Image":[{"url":"https://label-pomona.s3-ap-southeast-2.amazonaws.com/Crossroad-070419_221502-S437-E444.png"}],"Length (seconds)":7,"Start Time": "2019-04-07T22:22:19","Trap Number": "Secretary_Island/Crossroad" }},{"fields":{"Audio":[{"url": "https://label-pomona.s3-ap-southeast-2.amazonaws.com/Crossroad-070419_221502-S547-E554.wav"}],"Call Type":"Male","File Name":"Crossroad-070419_221502-S547-E554","Image":[{"url":"https://label-pomona.s3-ap-southeast-2.amazonaws.com/Crossroad-070419_221502-S547-E554.png"}],"Length (seconds)":7,"Start Time": "2019-04-07T22:24:09","Trap Number": "Secretary_Island/Crossroad" }},{"fields":{"Audio":[{"url": "https://label-pomona.s3-ap-southeast-2.amazonaws.com/Crossroad-070419_221502-S562-E569.wav"}],"Call Type":"Male","File Name":"Crossroad-070419_221502-S562-E569","Image":[{"url":"https://label-pomona.s3-ap-southeast-2.amazonaws.com/Crossroad-070419_221502-S562-E569.png"}],"Length (seconds)":7,"Start Time": "2019-04-07T22:24:24","Trap Number": "Secretary_Island/Crossroad" }},{"fields":{"Audio":[{"url": "https://label-pomona.s3-ap-southeast-2.amazonaws.com/Crossroad-070419_221502-S732-E742.wav"}],"Call Type":"Male","File Name":"Crossroad-070419_221502-S732-E742","Image":[{"url":"https://label-pomona.s3-ap-southeast-2.amazonaws.com/Crossroad-070419_221502-S732-E742.png"}],"Length (seconds)":10,"Start Time": "2019-04-07T22:27:14","Trap Number": "Secretary_Island/Crossroad" }}]}